core/__init__.py
core/arguments/ParseDictionaryArgs.py
core/arguments/__init__.py
core/arguments/command_line_arguments.py
core/constants/__init__.py
core/constants/not_available.py
core/environment/EnvironmentVariables.py
core/environment/__init__.py
core/exchange/ExchangeRate.py
core/exchange/InstrumentExchange.py
core/exchange/__init__.py
core/instant/RunInstantHolder.py
core/instant/__init__.py
core/missing/Context.py
core/missing/__init__.py
core/number/BigFloat.py
core/number/__init__.py
core/options/__init__.py
core/options/exception/MissingOptionError.py
core/options/exception/__init__.py
core/oracle/Prediction.py
core/oracle/__init__.py
core/position/Position.py
core/position/PositionSlip.py
core/position/__init__.py
core/trade/InstrumentTrade.py
core/trade/Order.py
core/trade/__init__.py
core/transform/Ignore.py
core/transform/__init__.py
persuader_technology_automata_core-0.6.0.dist-info/LICENSE
persuader_technology_automata_core-0.6.0.dist-info/METADATA
persuader_technology_automata_core-0.6.0.dist-info/WHEEL
persuader_technology_automata_core-0.6.0.dist-info/top_level.txt
persuader_technology_automata_core-0.6.0.dist-info/RECORD
