Metadata-Version: 2.1
Name: persuader-technology-automata-core
Version: 0.6.0
Summary: Automata Core
Author: Persuader Technology
Author-email: software@persuader.technology
License: UNLICENSE
Classifier: Programming Language :: Python :: 3
License-File: LICENSE
Requires-Dist: persuader-technology-automata-meta-info (>=0.0.3)
